lean_client/__init__.py
lean_client/client/__init__.py
lean_client/client/client.py
lean_client/client/aio/__init__.py
lean_client/client/aio/client.py
lean_client/proof/__init__.py
lean_client/proof/proto.py
lmms_lean_client-0.0.1.dev4.dist-info/METADATA
lmms_lean_client-0.0.1.dev4.dist-info/WHEEL
lmms_lean_client-0.0.1.dev4.dist-info/top_level.txt
lmms_lean_client-0.0.1.dev4.dist-info/RECORD
