Metadata-Version: 2.4
Name: lmms-lean-client
Version: 0.0.1.dev4
Summary: A Python client for the Lean Theorem Prover Server API.
Author-email: Pu Fanyi <FPU001@e.ntu.edu.sg>
Project-URL: Repository, https://github.com/pufanyi/lean-server
Keywords: lean,lean-client,lean-server,theorem prover
Classifier: Programming Language :: Python :: 3
Classifier: License :: OSI Approved :: MIT License
Classifier: Operating System :: OS Independent
Requires-Python: >=3.12
Requires-Dist: httpx>=0.27.0
Requires-Dist: pydantic>=2.0.0
Requires-Dist: tqdm>=4.67.1
